MANIFEST.in
README.rst
setup.cfg
setup.py
django_microsip.egg-info/PKG-INFO
django_microsip.egg-info/SOURCES.txt
django_microsip.egg-info/dependency_links.txt
django_microsip.egg-info/top_level.txt
microsip/__init__.py
microsip/__init__.pyc
microsip/comun/__init__.py
microsip/comun/__init__.pyc
microsip/comun/articulos/__init__.py
microsip/comun/articulos/__init__.pyc
microsip/comun/articulos/admin.pyc
microsip/comun/articulos/models.pyc
microsip/comun/articulos/tests.pyc
microsip/comun/articulos/views.pyc
microsip/comun/articulos/migrations/__init__.py
microsip/comun/articulos/migrations/__init__.pyc
microsip/comun/clientes/__init__.py
microsip/comun/clientes/__init__.pyc
microsip/comun/clientes/admin.pyc
microsip/comun/clientes/models.pyc
microsip/comun/clientes/models_changes_registry.pyc
microsip/comun/clientes/tests.pyc
microsip/comun/clientes/views.pyc
microsip/comun/clientes/migrations/__init__.py
microsip/comun/clientes/migrations/__init__.pyc
microsip/comun/direcciones/__init__.py
microsip/comun/direcciones/__init__.pyc
microsip/comun/direcciones/admin.pyc
microsip/comun/direcciones/models.pyc
microsip/comun/direcciones/tests.pyc
microsip/comun/direcciones/views.pyc
microsip/comun/direcciones/migrations/__init__.py
microsip/comun/direcciones/migrations/__init__.pyc
microsip/comun/general/__init__.py
microsip/comun/general/__init__.pyc
microsip/comun/general/admin.pyc
microsip/comun/general/models.pyc
microsip/comun/general/tests.pyc
microsip/comun/general/views.pyc
microsip/comun/general/migrations/__init__.py
microsip/comun/general/migrations/__init__.pyc
microsip/comun/impuestos/__init__.py
microsip/comun/impuestos/__init__.pyc
microsip/comun/impuestos/admin.pyc
microsip/comun/impuestos/models.pyc
microsip/comun/impuestos/tests.pyc
microsip/comun/impuestos/views.pyc
microsip/comun/impuestos/migrations/__init__.py
microsip/comun/impuestos/migrations/__init__.pyc
microsip/comun/listas/__init__.py
microsip/comun/listas/__init__.pyc
microsip/comun/listas/admin.pyc
microsip/comun/listas/models.pyc
microsip/comun/listas/tests.pyc
microsip/comun/listas/views.pyc
microsip/comun/listas/migrations/__init__.py
