Metadata-Version: 1.0
Name: django-microsip
Version: 0.0.16
Summary: A Django microsip app
Home-page: https://pypi.python.org/pypi/django-microsip-core
Author: Jesus Manuel Herrera Miramontes
Author-email: jesusmaherrera@gmail.com
License: BSD License
Platform: UNKNOWN
Classifier: Environment :: Web Environment
Classifier: Framework :: Django
Classifier: Intended Audience :: Developers
Classifier: License :: OSI Approved :: BSD License
Classifier: Operating System :: OS Independent
Classifier: Programming Language :: Python
Classifier: Programming Language :: Python :: 3
Classifier: Programming Language :: Python :: 3.2
Classifier: Programming Language :: Python :: 3.3
Classifier: Topic :: Internet :: WWW/HTTP
Classifier: Topic :: Internet :: WWW/HTTP :: Dynamic Content
